gittales/__init__.py
gittales/cli.py
gittales/core/__init__.py
gittales/core/analyzer.py
gittales/core/models.py
gittales/core/reader.py
gittales/reports/__init__.py
gittales/reports/console.py
gittales/utils/__init__.py
gittales/utils/helpers.py
gittales-0.1.7.dist-info/METADATA
gittales-0.1.7.dist-info/WHEEL
gittales-0.1.7.dist-info/entry_points.txt
gittales-0.1.7.dist-info/licenses/LICENSE
gittales-0.1.7.dist-info/RECORD
