Metadata-Version: 2.4
Name: gittales
Version: 0.1.7
Summary: Extract insights from your git commit history
Project-URL: Homepage, https://github.com/PatrickKalkman/gittales
Project-URL: Bug Tracker, https://github.com/PatrickKalkman/gittales/issues
Project-URL: Repository, https://github.com/PatrickKalkman/gittales.git
Author-email: Patrick Kalkman <patrick@simpletechture.nl>
License-Expression: MIT
License-File: LICENSE
Keywords: analytics,commit history,development insights,git,git analysis,software development
Classifier: Development Status :: 4 - Beta
Classifier: Intended Audience :: Developers
Classifier: Intended Audience :: Information Technology
Classifier: License :: OSI Approved :: MIT License
Classifier: Programming Language :: Python :: 3
Classifier: Programming Language :: Python :: 3.11
Classifier: Topic :: Software Development :: Libraries :: Python Modules
Classifier: Topic :: Software Development :: Version Control
Classifier: Topic :: Software Development :: Version Control :: Git
Requires-Python: >=3.11
Requires-Dist: gitpython>=3.1.44
Requires-Dist: langchain-core>=0.3.43
Requires-Dist: langchain-openai>=0.3.8
Requires-Dist: matplotlib>=3.10.1
Requires-Dist: pandas>=2.2.3
Requires-Dist: pydantic>=2.10.6
Requires-Dist: rich>=13.9.4
Requires-Dist: typer>=0.15.2
